hvcc_teensy/__init__.py
hvcc_teensy/main.py
hvcc_teensy/examples/crossover_noise/Makefile
hvcc_teensy/examples/crossover_noise/_main.pd
hvcc_teensy/examples/crossover_noise/crossover_noise.ino
hvcc_teensy/examples/crossover_noise/lr_crossover.pd
hvcc_teensy/examples/crossover_thru/Makefile
hvcc_teensy/examples/crossover_thru/_main.pd
hvcc_teensy/examples/crossover_thru/crossover_thru.ino
hvcc_teensy/examples/crossover_thru/lr_crossover.pd
hvcc_teensy/examples/sine_out/Makefile
hvcc_teensy/examples/sine_out/_main.pd
hvcc_teensy/examples/sine_out/sine_out.ino
hvcc_teensy/static/HvAudioProcessor.hpp
hvcc_teensy/templates/HeavyTeensy.h
hvcc_teensy-0.1.2.dist-info/METADATA
hvcc_teensy-0.1.2.dist-info/WHEEL
hvcc_teensy-0.1.2.dist-info/top_level.txt
hvcc_teensy-0.1.2.dist-info/RECORD
