Metadata-Version: 2.4
Name: hvcc_teensy
Version: 0.1.2
Summary: hvcc for Teensy
Author-email: Thomas Grill <gr@grrrr.org>
License-Expression: GPL-3.0-or-later
Project-URL: Homepage, https://github.com/grrrr/hvcc_teensy
Project-URL: Issues, https://github.com/grrrr/hvcc_teensy/issues
Classifier: Programming Language :: Python :: 3
Classifier: Development Status :: 3 - Alpha
Classifier: Operating System :: OS Independent
Classifier: Intended Audience :: Developers
Classifier: Topic :: Software Development :: Build Tools
Requires-Python: >=3.9
Requires-Dist: hvcc
